[
  {
    "id": 5190,
    "type": "instant",
    "field": "speed",
    "original_value": "70.0",
    "new_value": "5.4",
    "delta": "-64.64951179979644",
    "meta": {
      "carid": "XQR411",
      "grpid": "32"
    }
  },
  {
    "id": 5291,
    "type": "bias",
    "field": "direction",
    "original_value": "90.0",
    "new_value": "209.2",
    "delta": "119.17555489589896",
    "meta": {
      "carid": "X508W7",
      "grpid": "27"
    }
  },
  {
    "id": 5310,
    "type": "drift",
    "field": "latitude",
    "original_value": "22.576788",
    "new_value": "-18.568741",
    "delta": "-41.145528836855384",
    "meta": {
      "carid": "X253U7",
      "grpid": "34"
    }
  },
  {
    "id": 5354,
    "type": "instant",
    "field": "direction",
    "original_value": "90.0",
    "new_value": "6.1",
    "delta": "-83.91113387572614",
    "meta": {
      "carid": "X927G2",
      "grpid": "34"
    }
  },
  {
    "id": 5410,
    "type": "instant",
    "field": "longitude",
    "original_value": "114.120950",
    "new_value": "-105.781538",
    "delta": "-219.9024877356084",
    "meta": {
      "carid": "X57L80",
      "grpid": "38"
    }
  },
  {
    "id": 5467,
    "type": "bias",
    "field": "direction",
    "original_value": "180.0",
    "new_value": "282.2",
    "delta": "102.2422622757793",
    "meta": {
      "carid": "X508W7",
      "grpid": "28"
    }
  },
  {
    "id": 5471,
    "type": "instant",
    "field": "longitude",
    "original_value": "114.022250",
    "new_value": "-27.680651",
    "delta": "-141.70290108176857",
    "meta": {
      "carid": "X186F2",
      "grpid": "30"
    }
  },
  {
    "id": 5485,
    "type": "drift",
    "field": "latitude",
    "original_value": "22.575583",
    "new_value": "-57.339093",
    "delta": "-79.91467623716999",
    "meta": {
      "carid": "X253U7",
      "grpid": "35"
    }
  },
  {
    "id": 5506,
    "type": "instant",
    "field": "speed",
    "original_value": "32.0",
    "new_value": "59.7",
    "delta": "27.72570576299122",
    "meta": {
      "carid": "X169F0",
      "grpid": "34"
    }
  },
  {
    "id": 5584,
    "type": "drift",
    "field": "latitude",
    "original_value": "22.576796",
    "new_value": "-85.626728",
    "delta": "-108.20352364537545",
    "meta": {
      "carid": "X253U7",
      "grpid": "36"
    }
  },
  {
    "id": 5587,
    "type": "bias",
    "field": "longitude",
    "original_value": "114.055840",
    "new_value": "64.709796",
    "delta": "-49.34604374160277",
    "meta": {
      "carid": "X31G42",
      "grpid": "65"
    }
  },
  {
    "id": 5590,
    "type": "instant",
    "field": "latitude",
    "original_value": "22.523952",
    "new_value": "-28.442981",
    "delta": "-50.96693346112481",
    "meta": {
      "carid": "X56L55",
      "grpid": "64"
    }
  },
  {
    "id": 5594,
    "type": "bias",
    "field": "direction",
    "original_value": "315.0",
    "new_value": "146.4",
    "delta": "-168.64316906186193",
    "meta": {
      "carid": "X50F20",
      "grpid": "36"
    }
  },
  {
    "id": 5621,
    "type": "bias",
    "field": "latitude",
    "original_value": "22.542710",
    "new_value": "-59.637022",
    "delta": "-82.17973205405589",
    "meta": {
      "carid": "X989G5",
      "grpid": "34"
    }
  },
  {
    "id": 5629,
    "type": "bias",
    "field": "longitude",
    "original_value": "114.058080",
    "new_value": "168.622003",
    "delta": "54.56392348144017",
    "meta": {
      "carid": "X620D1",
      "grpid": "35"
    }
  },
  {
    "id": 5633,
    "type": "instant",
    "field": "longitude",
    "original_value": "114.027780",
    "new_value": "149.175528",
    "delta": "35.14774792903529",
    "meta": {
      "carid": "X508W7",
      "grpid": "30"
    }
  },
  {
    "id": 5647,
    "type": "instant",
    "field": "longitude",
    "original_value": "114.019844",
    "new_value": "-41.120519",
    "delta": "-155.14036256879308",
    "meta": {
      "carid": "X515W5",
      "grpid": "29"
    }
  },
  {
    "id": 5662,
    "type": "bias",
    "field": "longitude",
    "original_value": "114.059074",
    "new_value": "179.909832",
    "delta": "65.85075840620131",
    "meta": {
      "carid": "X31G42",
      "grpid": "66"
    }
  },
  {
    "id": 5716,
    "type": "drift",
    "field": "speed",
    "original_value": "0.0",
    "new_value": "49.4",
    "delta": "49.383258704001236",
    "meta": {
      "carid": "X917A2",
      "grpid": "37"
    }
  },
  {
    "id": 5738,
    "type": "bias",
    "field": "direction",
    "original_value": "0.0",
    "new_value": "164.8",
    "delta": "164.82671868706956",
    "meta": {
      "carid": "X50F20",
      "grpid": "37"
    }
  },
  {
    "id": 5758,
    "type": "bias",
    "field": "speed",
    "original_value": "18.0",
    "new_value": "117.9",
    "delta": "99.92776920635778",
    "meta": {
      "carid": "X357Z2",
      "grpid": "39"
    }
  },
  {
    "id": 5778,
    "type": "instant",
    "field": "longitude",
    "original_value": "114.037680",
    "new_value": "57.548622",
    "delta": "-56.48905835744613",
    "meta": {
      "carid": "X853U3",
      "grpid": "34"
    }
  },
  {
    "id": 5780,
    "type": "bias",
    "field": "longitude",
    "original_value": "114.056930",
    "new_value": "153.486751",
    "delta": "39.429821147067486",
    "meta": {
      "carid": "X620D1",
      "grpid": "36"
    }
  },
  {
    "id": 5788,
    "type": "bias",
    "field": "latitude",
    "original_value": "22.543364",
    "new_value": "11.790246",
    "delta": "-10.75311811289818",
    "meta": {
      "carid": "X989G5",
      "grpid": "35"
    }
  },
  {
    "id": 5823,
    "type": "bias",
    "field": "latitude",
    "original_value": "22.543724",
    "new_value": "-31.115617",
    "delta": "-53.65934088982111",
    "meta": {
      "carid": "X20S21",
      "grpid": "55"
    }
  },
  {
    "id": 5869,
    "type": "drift",
    "field": "speed",
    "original_value": "0.0",
    "new_value": "134.1",
    "delta": "134.10977317437695",
    "meta": {
      "carid": "X917A2",
      "grpid": "38"
    }
  },
  {
    "id": 5887,
    "type": "bias",
    "field": "speed",
    "original_value": "1.0",
    "new_value": "79.7",
    "delta": "78.71574574881075",
    "meta": {
      "carid": "XQR722",
      "grpid": "35"
    }
  },
  {
    "id": 5892,
    "type": "bias",
    "field": "direction",
    "original_value": "45.0",
    "new_value": "179.4",
    "delta": "134.35166189063045",
    "meta": {
      "carid": "X50F20",
      "grpid": "38"
    }
  },
  {
    "id": 5898,
    "type": "bias",
    "field": "latitude",
    "original_value": "22.545374",
    "new_value": "57.343215",
    "delta": "34.79784065849407",
    "meta": {
      "carid": "X20S21",
      "grpid": "56"
    }
  },
  {
    "id": 5925,
    "type": "instant",
    "field": "direction",
    "original_value": "180.0",
    "new_value": "7.1",
    "delta": "-172.91347759934564",
    "meta": {
      "carid": "X34G02",
      "grpid": "60"
    }
  },
  {
    "id": 5926,
    "type": "bias",
    "field": "speed",
    "original_value": "7.0",
    "new_value": "116.3",
    "delta": "109.29789469805007",
    "meta": {
      "carid": "X357Z2",
      "grpid": "40"
    }
  },
  {
    "id": 5945,
    "type": "instant",
    "field": "longitude",
    "original_value": "114.124985",
    "new_value": "-1.942949",
    "delta": "-116.06793367550692",
    "meta": {
      "carid": "X16V70",
      "grpid": "43"
    }
  },
  {
    "id": 5953,
    "type": "instant",
    "field": "direction",
    "original_value": "180.0",
    "new_value": "217.7",
    "delta": "37.672713062384446",
    "meta": {
      "carid": "X988G5",
      "grpid": "37"
    }
  },
  {
    "id": 5956,
    "type": "bias",
    "field": "latitude",
    "original_value": "22.543550",
    "new_value": "-65.326148",
    "delta": "-87.86969757617686",
    "meta": {
      "carid": "X989G5",
      "grpid": "36"
    }
  },
  {
    "id": 5982,
    "type": "instant",
    "field": "speed",
    "original_value": "60.0",
    "new_value": "26.4",
    "delta": "-33.634578194235374",
    "meta": {
      "carid": "X56L55",
      "grpid": "70"
    }
  },
  {
    "id": 6013,
    "type": "bias",
    "field": "speed",
    "original_value": "7.0",
    "new_value": "83.4",
    "delta": "76.35823859573222",
    "meta": {
      "carid": "XQR722",
      "grpid": "36"
    }
  },
  {
    "id": 6029,
    "type": "drift",
    "field": "speed",
    "original_value": "23.0",
    "new_value": "84.2",
    "delta": "61.24531544174516",
    "meta": {
      "carid": "X831U7",
      "grpid": "44"
    }
  },
  {
    "id": 6030,
    "type": "drift",
    "field": "speed",
    "original_value": "0.0",
    "new_value": "196.5",
    "delta": "196.48334403025447",
    "meta": {
      "carid": "X917A2",
      "grpid": "39"
    }
  },
  {
    "id": 6039,
    "type": "bias",
    "field": "longitude",
    "original_value": "114.046490",
    "new_value": "69.024751",
    "delta": "-45.02173889873055",
    "meta": {
      "carid": "X628Z0",
      "grpid": "36"
    }
  },
  {
    "id": 6040,
    "type": "instant",
    "field": "latitude",
    "original_value": "22.561400",
    "new_value": "-17.168147",
    "delta": "-39.72954744325301",
    "meta": {
      "carid": "X369R0",
      "grpid": "14"
    }
  },
  {
    "id": 6044,
    "type": "bias",
    "field": "longitude",
    "original_value": "114.071070",
    "new_value": "-166.553418",
    "delta": "-280.62448804603065",
    "meta": {
      "carid": "X867U1",
      "grpid": "37"
    }
  },
  {
    "id": 6070,
    "type": "instant",
    "field": "longitude",
    "original_value": "113.914380",
    "new_value": "18.023231",
    "delta": "-95.89114894782776",
    "meta": {
      "carid": "X20S11",
      "grpid": "55"
    }
  },
  {
    "id": 6122,
    "type": "bias",
    "field": "longitude",
    "original_value": "114.072060",
    "new_value": "-138.208749",
    "delta": "-252.2808085843633",
    "meta": {
      "carid": "X867U1",
      "grpid": "38"
    }
  },
  {
    "id": 6130,
    "type": "instant",
    "field": "longitude",
    "original_value": "114.158936",
    "new_value": "-51.356142",
    "delta": "-165.51507792843745",
    "meta": {
      "carid": "X802U7",
      "grpid": "40"
    }
  },
  {
    "id": 6147,
    "type": "instant",
    "field": "speed",
    "original_value": "0.0",
    "new_value": "99.2",
    "delta": "99.24777612897701",
    "meta": {
      "carid": "X403Z5",
      "grpid": "36"
    }
  },
  {
    "id": 6167,
    "type": "instant",
    "field": "longitude",
    "original_value": "114.104164",
    "new_value": "166.627153",
    "delta": "52.522988587510355",
    "meta": {
      "carid": "X38G95",
      "grpid": "56"
    }
  },
  {
    "id": 6198,
    "type": "bias",
    "field": "latitude",
    "original_value": "22.576288",
    "new_value": "-12.682272",
    "delta": "-35.25856039080994",
    "meta": {
      "carid": "X10S45",
      "grpid": "71"
    }
  },
  {
    "id": 6200,
    "type": "drift",
    "field": "speed",
    "original_value": "52.0",
    "new_value": "131.5",
    "delta": "79.47048917002618",
    "meta": {
      "carid": "X831U7",
      "grpid": "45"
    }
  },
  {
    "id": 6206,
    "type": "bias",
    "field": "longitude",
    "original_value": "114.050160",
    "new_value": "40.256918",
    "delta": "-73.79324162163424",
    "meta": {
      "carid": "X628Z0",
      "grpid": "37"
    }
  },
  {
    "id": 6212,
    "type": "instant",
    "field": "direction",
    "original_value": "315.0",
    "new_value": "140.7",
    "delta": "-174.26701458372176",
    "meta": {
      "carid": "X867U1",
      "grpid": "39"
    }
  },
  {
    "id": 6323,
    "type": "bias",
    "field": "direction",
    "original_value": "90.0",
    "new_value": "16.3",
    "delta": "-73.74516693700025",
    "meta": {
      "carid": "X166F7",
      "grpid": "36"
    }
  },
  {
    "id": 6361,
    "type": "bias",
    "field": "latitude",
    "original_value": "22.572940",
    "new_value": "-48.644787",
    "delta": "-71.21772669305774",
    "meta": {
      "carid": "X10S45",
      "grpid": "72"
    }
  },
  {
    "id": 6369,
    "type": "bias",
    "field": "longitude",
    "original_value": "114.056114",
    "new_value": "-99.611845",
    "delta": "-213.66795892428632",
    "meta": {
      "carid": "X628Z0",
      "grpid": "38"
    }
  },
  {
    "id": 6385,
    "type": "bias",
    "field": "direction",
    "original_value": "135.0",
    "new_value": "183.7",
    "delta": "48.678856342529",
    "meta": {
      "carid": "X364K5",
      "grpid": "37"
    }
  },
  {
    "id": 6423,
    "type": "bias",
    "field": "latitude",
    "original_value": "22.621532",
    "new_value": "-79.214728",
    "delta": "-101.83626035213057",
    "meta": {
      "carid": "X408Z7",
      "grpid": "43"
    }
  },
  {
    "id": 6490,
    "type": "bias",
    "field": "direction",
    "original_value": "90.0",
    "new_value": "306.2",
    "delta": "216.1832776744239",
    "meta": {
      "carid": "X166F7",
      "grpid": "37"
    }
  },
  {
    "id": 6503,
    "type": "drift",
    "field": "speed",
    "original_value": "0.0",
    "new_value": "236.9",
    "delta": "236.90643665190055",
    "meta": {
      "carid": "XQR741",
      "grpid": "43"
    }
  },
  {
    "id": 6546,
    "type": "drift",
    "field": "longitude",
    "original_value": "113.818474",
    "new_value": "-95.545432",
    "delta": "-209.36390594360526",
    "meta": {
      "carid": "X341U2",
      "grpid": "45"
    }
  },
  {
    "id": 6556,
    "type": "bias",
    "field": "direction",
    "original_value": "135.0",
    "new_value": "182.6",
    "delta": "47.60273908280769",
    "meta": {
      "carid": "X364K5",
      "grpid": "38"
    }
  },
  {
    "id": 6561,
    "type": "bias",
    "field": "speed",
    "original_value": "34.0",
    "new_value": "1.7",
    "delta": "-32.299774640986044",
    "meta": {
      "carid": "X65F70",
      "grpid": "42"
    }
  },
  {
    "id": 6577,
    "type": "instant",
    "field": "latitude",
    "original_value": "22.520000",
    "new_value": "70.092605",
    "delta": "47.57260549057811",
    "meta": {
      "carid": "X766D3",
      "grpid": "43"
    }
  },
  {
    "id": 6581,
    "type": "instant",
    "field": "speed",
    "original_value": "6.0",
    "new_value": "166.4",
    "delta": "160.39454618938615",
    "meta": {
      "carid": "X332D7",
      "grpid": "43"
    }
  },
  {
    "id": 6592,
    "type": "bias",
    "field": "latitude",
    "original_value": "22.619938",
    "new_value": "-2.825162",
    "delta": "-25.445100025095922",
    "meta": {
      "carid": "X408Z7",
      "grpid": "44"
    }
  },
  {
    "id": 6637,
    "type": "bias",
    "field": "speed",
    "original_value": "0.0",
    "new_value": "43.8",
    "delta": "43.833219373619585",
    "meta": {
      "carid": "X98P21",
      "grpid": "43"
    }
  },
  {
    "id": 6642,
    "type": "instant",
    "field": "longitude",
    "original_value": "113.894196",
    "new_value": "-146.301564",
    "delta": "-260.19576002991414",
    "meta": {
      "carid": "X306U0",
      "grpid": "37"
    }
  },
  {
    "id": 6647,
    "type": "instant",
    "field": "speed",
    "original_value": "19.0",
    "new_value": "147.6",
    "delta": "128.6017542838878",
    "meta": {
      "carid": "X17G05",
      "grpid": "116"
    }
  },
  {
    "id": 6672,
    "type": "drift",
    "field": "speed",
    "original_value": "0.0",
    "new_value": "242.1",
    "delta": "242.0712866446439",
    "meta": {
      "carid": "XQR741",
      "grpid": "44"
    }
  },
  {
    "id": 6688,
    "type": "instant",
    "field": "speed",
    "original_value": "41.0",
    "new_value": "113.5",
    "delta": "72.4822972737533",
    "meta": {
      "carid": "X35G10",
      "grpid": "59"
    }
  },
  {
    "id": 6716,
    "type": "bias",
    "field": "speed",
    "original_value": "0.0",
    "new_value": "126.5",
    "delta": "126.49858096120562",
    "meta": {
      "carid": "X65F70",
      "grpid": "43"
    }
  },
  {
    "id": 6719,
    "type": "drift",
    "field": "longitude",
    "original_value": "113.823640",
    "new_value": "-167.989828",
    "delta": "-281.81346756404275",
    "meta": {
      "carid": "X341U2",
      "grpid": "46"
    }
  },
  {
    "id": 6752,
    "type": "instant",
    "field": "direction",
    "original_value": "180.0",
    "new_value": "116.1",
    "delta": "-63.864241900268254",
    "meta": {
      "carid": "X20S50",
      "grpid": "76"
    }
  },
  {
    "id": 6753,
    "type": "bias",
    "field": "direction",
    "original_value": "45.0",
    "new_value": "341.0",
    "delta": "295.9962930808493",
    "meta": {
      "carid": "X35G87",
      "grpid": "75"
    }
  },
  {
    "id": 6762,
    "type": "bias",
    "field": "direction",
    "original_value": "0.0",
    "new_value": "279.7",
    "delta": "279.7305330130233",
    "meta": {
      "carid": "X35G87",
      "grpid": "76"
    }
  },
  {
    "id": 6763,
    "type": "bias",
    "field": "longitude",
    "original_value": "113.982130",
    "new_value": "-66.487306",
    "delta": "-180.4694359505956",
    "meta": {
      "carid": "X21S13",
      "grpid": "79"
    }
  },
  {
    "id": 6781,
    "type": "bias",
    "field": "longitude",
    "original_value": "114.029060",
    "new_value": "-41.305320",
    "delta": "-155.334379771638",
    "meta": {
      "carid": "X51L73",
      "grpid": "79"
    }
  },
  {
    "id": 6783,
    "type": "instant",
    "field": "latitude",
    "original_value": "22.559975",
    "new_value": "-55.952464",
    "delta": "-78.51243903822458",
    "meta": {
      "carid": "X967G2",
      "grpid": "41"
    }
  },
  {
    "id": 6788,
    "type": "bias",
    "field": "speed",
    "original_value": "22.0",
    "new_value": "159.0",
    "delta": "137.02946239431898",
    "meta": {
      "carid": "X98P21",
      "grpid": "44"
    }
  },
  {
    "id": 6794,
    "type": "instant",
    "field": "longitude",
    "original_value": "114.158936",
    "new_value": "1.516600",
    "delta": "-112.64233601922388",
    "meta": {
      "carid": "X802U7",
      "grpid": "44"
    }
  },
  {
    "id": 6801,
    "type": "bias",
    "field": "latitude",
    "original_value": "22.657686",
    "new_value": "7.189327",
    "delta": "-15.468358651207154",
    "meta": {
      "carid": "X508W7",
      "grpid": "38"
    }
  },
  {
    "id": 6803,
    "type": "drift",
    "field": "longitude",
    "original_value": "114.086720",
    "new_value": "46.191050",
    "delta": "-67.89566976605364",
    "meta": {
      "carid": "X987G3",
      "grpid": "40"
    }
  },
  {
    "id": 6809,
    "type": "bias",
    "field": "longitude",
    "original_value": "113.978990",
    "new_value": "59.726763",
    "delta": "-54.25222673466255",
    "meta": {
      "carid": "X21S13",
      "grpid": "80"
    }
  },
  {
    "id": 6819,
    "type": "bias",
    "field": "longitude",
    "original_value": "114.029090",
    "new_value": "-6.161964",
    "delta": "-120.19105354202675",
    "meta": {
      "carid": "X51L73",
      "grpid": "80"
    }
  },
  {
    "id": 6883,
    "type": "instant",
    "field": "latitude",
    "original_value": "22.681778",
    "new_value": "-74.497417",
    "delta": "-97.17919532070835",
    "meta": {
      "carid": "X341U2",
      "grpid": "47"
    }
  },
  {
    "id": 6888,
    "type": "drift",
    "field": "longitude",
    "original_value": "114.105530",
    "new_value": "57.767802",
    "delta": "-56.33772819018678",
    "meta": {
      "carid": "X332D7",
      "grpid": "45"
    }
  },
  {
    "id": 6918,
    "type": "bias",
    "field": "direction",
    "original_value": "45.0",
    "new_value": "167.7",
    "delta": "122.71679081720075",
    "meta": {
      "carid": "X35G87",
      "grpid": "77"
    }
  },
  {
    "id": 6931,
    "type": "bias",
    "field": "longitude",
    "original_value": "113.969650",
    "new_value": "-111.124649",
    "delta": "-225.09429894298324",
    "meta": {
      "carid": "X21S13",
      "grpid": "81"
    }
  },
  {
    "id": 6937,
    "type": "drift",
    "field": "direction",
    "original_value": "90.0",
    "new_value": "130.9",
    "delta": "40.911136669366186",
    "meta": {
      "carid": "X333U5",
      "grpid": "46"
    }
  },
  {
    "id": 6941,
    "type": "bias",
    "field": "speed",
    "original_value": "14.0",
    "new_value": "83.6",
    "delta": "69.62328506300517",
    "meta": {
      "carid": "X98P21",
      "grpid": "45"
    }
  },
  {
    "id": 6943,
    "type": "bias",
    "field": "speed",
    "original_value": "44.0",
    "new_value": "71.1",
    "delta": "27.143905930589582",
    "meta": {
      "carid": "X853U3",
      "grpid": "41"
    }
  },
  {
    "id": 6945,
    "type": "bias",
    "field": "longitude",
    "original_value": "114.066246",
    "new_value": "90.405686",
    "delta": "-23.660559828339146",
    "meta": {
      "carid": "X20S43",
      "grpid": "80"
    }
  },
  {
    "id": 6952,
    "type": "bias",
    "field": "longitude",
    "original_value": "114.031810",
    "new_value": "53.200151",
    "delta": "-60.831659165171445",
    "meta": {
      "carid": "X51L73",
      "grpid": "81"
    }
  },
  {
    "id": 6954,
    "type": "instant",
    "field": "latitude",
    "original_value": "22.558796",
    "new_value": "84.453639",
    "delta": "61.89484301338722",
    "meta": {
      "carid": "X967G2",
      "grpid": "42"
    }
  },
  {
    "id": 6957,
    "type": "drift",
    "field": "speed",
    "original_value": "0.0",
    "new_value": "65.8",
    "delta": "65.8402730745183",
    "meta": {
      "carid": "X761D7",
      "grpid": "41"
    }
  },
  {
    "id": 6962,
    "type": "bias",
    "field": "speed",
    "original_value": "0.0",
    "new_value": "69.8",
    "delta": "69.81906180767957",
    "meta": {
      "carid": "X36G92",
      "grpid": "70"
    }
  },
  {
    "id": 6964,
    "type": "drift",
    "field": "latitude",
    "original_value": "22.546432",
    "new_value": "45.411553",
    "delta": "22.865121493148234",
    "meta": {
      "carid": "XA3F64",
      "grpid": "45"
    }
  },
  {
    "id": 6967,
    "type": "bias",
    "field": "latitude",
    "original_value": "22.656242",
    "new_value": "-65.713934",
    "delta": "-88.37017621800922",
    "meta": {
      "carid": "X508W7",
      "grpid": "39"
    }
  },
  {
    "id": 6969,
    "type": "drift",
    "field": "longitude",
    "original_value": "114.086720",
    "new_value": "-44.303680",
    "delta": "-158.3903996546384",
    "meta": {
      "carid": "X987G3",
      "grpid": "41"
    }
  },
  {
    "id": 7004,
    "type": "bias",
    "field": "longitude",
    "original_value": "114.065895",
    "new_value": "-31.500868",
    "delta": "-145.56676250898758",
    "meta": {
      "carid": "X20S43",
      "grpid": "81"
    }
  },
  {
    "id": 7040,
    "type": "instant",
    "field": "direction",
    "original_value": "0.0",
    "new_value": "222.1",
    "delta": "222.1182866850299",
    "meta": {
      "carid": "X20S52",
      "grpid": "54"
    }
  },
  {
    "id": 7047,
    "type": "drift",
    "field": "longitude",
    "original_value": "114.105130",
    "new_value": "-122.229219",
    "delta": "-236.33434910700177",
    "meta": {
      "carid": "X332D7",
      "grpid": "46"
    }
  },
  {
    "id": 7053,
    "type": "bias",
    "field": "latitude",
    "original_value": "22.556868",
    "new_value": "-14.927848",
    "delta": "-37.4847164792661",
    "meta": {
      "carid": "X47G73",
      "grpid": "65"
    }
  },
  {
    "id": 7083,
    "type": "bias",
    "field": "speed",
    "original_value": "0.0",
    "new_value": "140.5",
    "delta": "140.45446303176172",
    "meta": {
      "carid": "X36G92",
      "grpid": "71"
    }
  },
  {
    "id": 7106,
    "type": "drift",
    "field": "direction",
    "original_value": "90.0",
    "new_value": "280.4",
    "delta": "190.39067955736266",
    "meta": {
      "carid": "X333U5",
      "grpid": "47"
    }
  },
  {
    "id": 7109,
    "type": "bias",
    "field": "speed",
    "original_value": "34.0",
    "new_value": "213.3",
    "delta": "179.27862714723884",
    "meta": {
      "carid": "X853U3",
      "grpid": "42"
    }
  },
  {
    "id": 7111,
    "type": "bias",
    "field": "longitude",
    "original_value": "114.065384",
    "new_value": "-158.063432",
    "delta": "-272.1288164554246",
    "meta": {
      "carid": "X20S43",
      "grpid": "82"
    }
  },
  {
    "id": 7116,
    "type": "drift",
    "field": "latitude",
    "original_value": "22.547268",
    "new_value": "77.362124",
    "delta": "54.81485609582414",
    "meta": {
      "carid": "XA3F64",
      "grpid": "46"
    }
  },
  {
    "id": 7125,
    "type": "drift",
    "field": "speed",
    "original_value": "0.0",
    "new_value": "88.1",
    "delta": "88.10311166802778",
    "meta": {
      "carid": "X761D7",
      "grpid": "42"
    }
  },
  {
    "id": 7174,
    "type": "instant",
    "field": "speed",
    "original_value": "49.0",
    "new_value": "103.9",
    "delta": "54.94193585083586",
    "meta": {
      "carid": "X169F0",
      "grpid": "44"
    }
  },
  {
    "id": 7188,
    "type": "drift",
    "field": "speed",
    "original_value": "84.0",
    "new_value": "193.1",
    "delta": "109.08460917777717",
    "meta": {
      "carid": "X831U7",
      "grpid": "46"
    }
  },
  {
    "id": 7191,
    "type": "bias",
    "field": "speed",
    "original_value": "0.0",
    "new_value": "123.1",
    "delta": "123.10498486072505",
    "meta": {
      "carid": "XQR423",
      "grpid": "46"
    }
  },
  {
    "id": 7196,
    "type": "drift",
    "field": "direction",
    "original_value": "90.0",
    "new_value": "131.1",
    "delta": "41.080362122361464",
    "meta": {
      "carid": "X766D3",
      "grpid": "47"
    }
  },
  {
    "id": 7219,
    "type": "bias",
    "field": "latitude",
    "original_value": "22.556852",
    "new_value": "-59.151953",
    "delta": "-81.70880548303347",
    "meta": {
      "carid": "X47G73",
      "grpid": "66"
    }
  },
  {
    "id": 7220,
    "type": "drift",
    "field": "direction",
    "original_value": "270.0",
    "new_value": "346.8",
    "delta": "76.75773423136923",
    "meta": {
      "carid": "X95P51",
      "grpid": "47"
    }
  },
  {
    "id": 7230,
    "type": "instant",
    "field": "longitude",
    "original_value": "114.129350",
    "new_value": "147.452171",
    "delta": "33.32282060933993",
    "meta": {
      "carid": "X56L62",
      "grpid": "61"
    }
  },
  {
    "id": 7245,
    "type": "bias",
    "field": "speed",
    "original_value": "0.0",
    "new_value": "140.2",
    "delta": "140.1946978261156",
    "meta": {
      "carid": "XA5P72",
      "grpid": "86"
    }
  },
  {
    "id": 7276,
    "type": "bias",
    "field": "latitude",
    "original_value": "22.655928",
    "new_value": "75.018300",
    "delta": "52.36237214692646",
    "meta": {
      "carid": "X853U3",
      "grpid": "43"
    }
  },
  {
    "id": 7277,
    "type": "bias",
    "field": "direction",
    "original_value": "135.0",
    "new_value": "62.8",
    "delta": "-72.23572325181117",
    "meta": {
      "carid": "XA3K31",
      "grpid": "48"
    }
  },
  {
    "id": 7283,
    "type": "instant",
    "field": "latitude",
    "original_value": "22.674423",
    "new_value": "49.316500",
    "delta": "26.642076928709127",
    "meta": {
      "carid": "X491W3",
      "grpid": "35"
    }
  },
  {
    "id": 7290,
    "type": "drift",
    "field": "speed",
    "original_value": "0.0",
    "new_value": "218.4",
    "delta": "218.4118516837673",
    "meta": {
      "carid": "X761D7",
      "grpid": "43"
    }
  },
  {
    "id": 7337,
    "type": "bias",
    "field": "speed",
    "original_value": "0.0",
    "new_value": "108.7",
    "delta": "108.74702155966986",
    "meta": {
      "carid": "XA5P72",
      "grpid": "87"
    }
  },
  {
    "id": 7347,
    "type": "instant",
    "field": "latitude",
    "original_value": "22.560844",
    "new_value": "54.631336",
    "delta": "32.0704918629762",
    "meta": {
      "carid": "X56L35",
      "grpid": "82"
    }
  },
  {
    "id": 7352,
    "type": "drift",
    "field": "direction",
    "original_value": "90.0",
    "new_value": "141.6",
    "delta": "51.598915058264566",
    "meta": {
      "carid": "X766D3",
      "grpid": "48"
    }
  },
  {
    "id": 7354,
    "type": "instant",
    "field": "longitude",
    "original_value": "114.129530",
    "new_value": "74.562326",
    "delta": "-39.56720405835779",
    "meta": {
      "carid": "XQR422",
      "grpid": "47"
    }
  },
  {
    "id": 7358,
    "type": "bias",
    "field": "speed",
    "original_value": "0.0",
    "new_value": "88.2",
    "delta": "88.24827579180244",
    "meta": {
      "carid": "XQR423",
      "grpid": "47"
    }
  },
  {
    "id": 7373,
    "type": "drift",
    "field": "direction",
    "original_value": "225.0",
    "new_value": "353.6",
    "delta": "128.55086420380792",
    "meta": {
      "carid": "X95P51",
      "grpid": "48"
    }
  },
  {
    "id": 7406,
    "type": "bias",
    "field": "latitude",
    "original_value": "22.537874",
    "new_value": "60.975118",
    "delta": "38.43724425616895",
    "meta": {
      "carid": "X57L82",
      "grpid": "74"
    }
  },
  {
    "id": 7408,
    "type": "bias",
    "field": "speed",
    "original_value": "0.0",
    "new_value": "237.4",
    "delta": "237.3957182229709",
    "meta": {
      "carid": "XA5P72",
      "grpid": "88"
    }
  },
  {
    "id": 7432,
    "type": "bias",
    "field": "direction",
    "original_value": "135.0",
    "new_value": "8.4",
    "delta": "-126.59390517296826",
    "meta": {
      "carid": "XA3K31",
      "grpid": "49"
    }
  },
  {
    "id": 7438,
    "type": "instant",
    "field": "latitude",
    "original_value": "22.543295",
    "new_value": "-81.216545",
    "delta": "-103.7598396338295",
    "meta": {
      "carid": "X962G0",
      "grpid": "49"
    }
  },
  {
    "id": 7439,
    "type": "instant",
    "field": "direction",
    "original_value": "180.0",
    "new_value": "74.5",
    "delta": "-105.5388125323026",
    "meta": {
      "carid": "X76F60",
      "grpid": "48"
    }
  },
  {
    "id": 7440,
    "type": "bias",
    "field": "latitude",
    "original_value": "22.655333",
    "new_value": "-52.787873",
    "delta": "-75.44320567931936",
    "meta": {
      "carid": "X853U3",
      "grpid": "44"
    }
  },
  {
    "id": 7497,
    "type": "drift",
    "field": "speed",
    "original_value": "0.0",
    "new_value": "32.2",
    "delta": "32.20377052195582",
    "meta": {
      "carid": "XQR741",
      "grpid": "49"
    }
  },
  {
    "id": 7521,
    "type": "instant",
    "field": "latitude",
    "original_value": "22.612362",
    "new_value": "-46.015597",
    "delta": "-68.62795917135902",
    "meta": {
      "carid": "X52L22",
      "grpid": "86"
    }
  },
  {
    "id": 7532,
    "type": "instant",
    "field": "latitude",
    "original_value": "22.568167",
    "new_value": "-32.142815",
    "delta": "-54.710981851129844",
    "meta": {
      "carid": "X28X43",
      "grpid": "49"
    }
  },
  {
    "id": 7571,
    "type": "bias",
    "field": "latitude",
    "original_value": "22.541637",
    "new_value": "-29.120928",
    "delta": "-51.6625645421669",
    "meta": {
      "carid": "X57L82",
      "grpid": "75"
    }
  },
  {
    "id": 7579,
    "type": "bias",
    "field": "direction",
    "original_value": "135.0",
    "new_value": "333.3",
    "delta": "198.2826791838745",
    "meta": {
      "carid": "XA3K31",
      "grpid": "50"
    }
  },
  {
    "id": 7621,
    "type": "instant",
    "field": "speed",
    "original_value": "0.0",
    "new_value": "233.8",
    "delta": "233.81919988333428",
    "meta": {
      "carid": "X761D7",
      "grpid": "45"
    }
  },
  {
    "id": 7629,
    "type": "bias",
    "field": "speed",
    "original_value": "0.0",
    "new_value": "97.9",
    "delta": "97.90088795894833",
    "meta": {
      "carid": "X412Y0",
      "grpid": "160"
    }
  },
  {
    "id": 7664,
    "type": "drift",
    "field": "speed",
    "original_value": "0.0",
    "new_value": "90.0",
    "delta": "90.0333513305309",
    "meta": {
      "carid": "XQR741",
      "grpid": "50"
    }
  },
  {
    "id": 7693,
    "type": "bias",
    "field": "speed",
    "original_value": "0.0",
    "new_value": "28.0",
    "delta": "27.956541247949744",
    "meta": {
      "carid": "X412Y0",
      "grpid": "161"
    }
  },
  {
    "id": 7709,
    "type": "instant",
    "field": "speed",
    "original_value": "60.0",
    "new_value": "192.8",
    "delta": "132.75761886373465",
    "meta": {
      "carid": "XQR411",
      "grpid": "49"
    }
  },
  {
    "id": 7717,
    "type": "instant",
    "field": "latitude",
    "original_value": "22.715048",
    "new_value": "-50.488752",
    "delta": "-73.20379989685718",
    "meta": {
      "carid": "X341U2",
      "grpid": "52"
    }
  },
  {
    "id": 7733,
    "type": "bias",
    "field": "speed",
    "original_value": "0.0",
    "new_value": "130.7",
    "delta": "130.68451466172652",
    "meta": {
      "carid": "X412Y0",
      "grpid": "162"
    }
  },
  {
    "id": 7744,
    "type": "instant",
    "field": "direction",
    "original_value": "270.0",
    "new_value": "194.7",
    "delta": "-75.2719631552497",
    "meta": {
      "carid": "X287K7",
      "grpid": "45"
    }
  },
  {
    "id": 7808,
    "type": "instant",
    "field": "latitude",
    "original_value": "22.539080",
    "new_value": "-76.563900",
    "delta": "-99.10298031268107",
    "meta": {
      "carid": "XQR420",
      "grpid": "48"
    }
  },
  {
    "id": 7813,
    "type": "drift",
    "field": "latitude",
    "original_value": "22.541218",
    "new_value": "33.555495",
    "delta": "11.014276721594449",
    "meta": {
      "carid": "X31W87",
      "grpid": "51"
    }
  },
  {
    "id": 7835,
    "type": "drift",
    "field": "speed",
    "original_value": "0.0",
    "new_value": "126.7",
    "delta": "126.70599577323897",
    "meta": {
      "carid": "XQR741",
      "grpid": "51"
    }
  },
  {
    "id": 7911,
    "type": "instant",
    "field": "longitude",
    "original_value": "113.947230",
    "new_value": "92.519896",
    "delta": "-21.42733428264812",
    "meta": {
      "carid": "X163F3",
      "grpid": "48"
    }
  },
  {
    "id": 7918,
    "type": "instant",
    "field": "speed",
    "original_value": "66.0",
    "new_value": "25.7",
    "delta": "-40.31366246217835",
    "meta": {
      "carid": "X620D1",
      "grpid": "50"
    }
  },
  {
    "id": 7970,
    "type": "drift",
    "field": "latitude",
    "original_value": "22.541218",
    "new_value": "88.436334",
    "delta": "65.89511611068188",
    "meta": {
      "carid": "X31W87",
      "grpid": "52"
    }
  },
  {
    "id": 8009,
    "type": "instant",
    "field": "speed",
    "original_value": "12.0",
    "new_value": "224.0",
    "delta": "211.9522468658841",
    "meta": {
      "carid": "X989G3",
      "grpid": "49"
    }
  },
  {
    "id": 8046,
    "type": "instant",
    "field": "speed",
    "original_value": "0.0",
    "new_value": "207.7",
    "delta": "207.69813844450573",
    "meta": {
      "carid": "X43F95",
      "grpid": "90"
    }
  },
  {
    "id": 8078,
    "type": "instant",
    "field": "latitude",
    "original_value": "22.544182",
    "new_value": "-30.357585",
    "delta": "-52.90176669927249",
    "meta": {
      "carid": "X56L83",
      "grpid": "92"
    }
  },
  {
    "id": 8128,
    "type": "drift",
    "field": "latitude",
    "original_value": "22.688477",
    "new_value": "-1.788419",
    "delta": "-24.476896263292808",
    "meta": {
      "carid": "X452W7",
      "grpid": "52"
    }
  },
  {
    "id": 8204,
    "type": "instant",
    "field": "direction",
    "original_value": "315.0",
    "new_value": "262.1",
    "delta": "-52.8648514392367",
    "meta": {
      "carid": "X628Z0",
      "grpid": "49"
    }
  },
  {
    "id": 8229,
    "type": "bias",
    "field": "direction",
    "original_value": "225.0",
    "new_value": "263.4",
    "delta": "38.4236214031593",
    "meta": {
      "carid": "XA5G44",
      "grpid": "53"
    }
  },
  {
    "id": 8236,
    "type": "instant",
    "field": "direction",
    "original_value": "270.0",
    "new_value": "117.8",
    "delta": "-152.19318011314348",
    "meta": {
      "carid": "X16V70",
      "grpid": "58"
    }
  },
  {
    "id": 8240,
    "type": "drift",
    "field": "direction",
    "original_value": "270.0",
    "new_value": "141.7",
    "delta": "-128.2791806861985",
    "meta": {
      "carid": "X52D05",
      "grpid": "43"
    }
  },
  {
    "id": 8293,
    "type": "drift",
    "field": "latitude",
    "original_value": "22.689362",
    "new_value": "-23.378039",
    "delta": "-46.06740096900934",
    "meta": {
      "carid": "X452W7",
      "grpid": "53"
    }
  },
  {
    "id": 8313,
    "type": "instant",
    "field": "speed",
    "original_value": "58.0",
    "new_value": "242.4",
    "delta": "184.39505272529755",
    "meta": {
      "carid": "X403Z5",
      "grpid": "49"
    }
  },
  {
    "id": 8392,
    "type": "bias",
    "field": "direction",
    "original_value": "270.0",
    "new_value": "176.7",
    "delta": "-93.30671812357045",
    "meta": {
      "carid": "XA5G44",
      "grpid": "54"
    }
  },
  {
    "id": 8397,
    "type": "bias",
    "field": "direction",
    "original_value": "135.0",
    "new_value": "244.6",
    "delta": "109.61654663056939",
    "meta": {
      "carid": "X17G05",
      "grpid": "148"
    }
  },
  {
    "id": 8401,
    "type": "bias",
    "field": "direction",
    "original_value": "135.0",
    "new_value": "348.7",
    "delta": "213.67624019691613",
    "meta": {
      "carid": "X17G05",
      "grpid": "149"
    }
  },
  {
    "id": 8405,
    "type": "instant",
    "field": "latitude",
    "original_value": "22.558453",
    "new_value": "10.846374",
    "delta": "-11.712078580336936",
    "meta": {
      "carid": "X38G91",
      "grpid": "84"
    }
  },
  {
    "id": 8409,
    "type": "drift",
    "field": "direction",
    "original_value": "225.0",
    "new_value": "89.8",
    "delta": "-135.20362953015552",
    "meta": {
      "carid": "X52D05",
      "grpid": "44"
    }
  },
  {
    "id": 8466,
    "type": "instant",
    "field": "speed",
    "original_value": "0.0",
    "new_value": "97.8",
    "delta": "97.7691414046186",
    "meta": {
      "carid": "X35G10",
      "grpid": "81"
    }
  },
  {
    "id": 8467,
    "type": "drift",
    "field": "latitude",
    "original_value": "22.690556",
    "new_value": "-86.558998",
    "delta": "-109.24955351552298",
    "meta": {
      "carid": "X452W7",
      "grpid": "54"
    }
  },
  {
    "id": 8485,
    "type": "bias",
    "field": "direction",
    "original_value": "135.0",
    "new_value": "194.7",
    "delta": "59.675239697992595",
    "meta": {
      "carid": "X17G05",
      "grpid": "150"
    }
  },
  {
    "id": 8527,
    "type": "drift",
    "field": "speed",
    "original_value": "0.0",
    "new_value": "90.6",
    "delta": "90.59429901954117",
    "meta": {
      "carid": "X780D2",
      "grpid": "55"
    }
  },
  {
    "id": 8547,
    "type": "bias",
    "field": "direction",
    "original_value": "180.0",
    "new_value": "344.9",
    "delta": "164.86315744366823",
    "meta": {
      "carid": "XA5G44",
      "grpid": "55"
    }
  },
  {
    "id": 8575,
    "type": "drift",
    "field": "direction",
    "original_value": "315.0",
    "new_value": "72.6",
    "delta": "-242.40327837700494",
    "meta": {
      "carid": "X52D05",
      "grpid": "45"
    }
  },
  {
    "id": 8594,
    "type": "bias",
    "field": "speed",
    "original_value": "0.0",
    "new_value": "114.1",
    "delta": "114.13113709894735",
    "meta": {
      "carid": "X57L82",
      "grpid": "82"
    }
  },
  {
    "id": 8619,
    "type": "bias",
    "field": "direction",
    "original_value": "135.0",
    "new_value": "3.9",
    "delta": "-131.12085536316334",
    "meta": {
      "carid": "X333U5",
      "grpid": "57"
    }
  },
  {
    "id": 8668,
    "type": "instant",
    "field": "longitude",
    "original_value": "114.062100",
    "new_value": "-143.958188",
    "delta": "-258.020287540218",
    "meta": {
      "carid": "X376Z2",
      "grpid": "50"
    }
  },
  {
    "id": 8672,
    "type": "instant",
    "field": "longitude",
    "original_value": "114.006645",
    "new_value": "-144.651051",
    "delta": "-258.6576961396619",
    "meta": {
      "carid": "X433Z2",
      "grpid": "53"
    }
  },
  {
    "id": 8680,
    "type": "drift",
    "field": "speed",
    "original_value": "0.0",
    "new_value": "94.5",
    "delta": "94.45346896167503",
    "meta": {
      "carid": "X780D2",
      "grpid": "56"
    }
  },
  {
    "id": 8709,
    "type": "bias",
    "field": "direction",
    "original_value": "225.0",
    "new_value": "332.3",
    "delta": "107.33187572124405",
    "meta": {
      "carid": "XA5G44",
      "grpid": "56"
    }
  },
  {
    "id": 8733,
    "type": "bias",
    "field": "speed",
    "original_value": "0.0",
    "new_value": "54.1",
    "delta": "54.1163853951313",
    "meta": {
      "carid": "X364K5",
      "grpid": "51"
    }
  },
  {
    "id": 8763,
    "type": "bias",
    "field": "speed",
    "original_value": "0.0",
    "new_value": "56.6",
    "delta": "56.58846859637026",
    "meta": {
      "carid": "X57L82",
      "grpid": "83"
    }
  },
  {
    "id": 8787,
    "type": "bias",
    "field": "direction",
    "original_value": "45.0",
    "new_value": "96.8",
    "delta": "51.785615971911724",
    "meta": {
      "carid": "X333U5",
      "grpid": "58"
    }
  },
  {
    "id": 8807,
    "type": "instant",
    "field": "direction",
    "original_value": "270.0",
    "new_value": "354.1",
    "delta": "84.07980122643045",
    "meta": {
      "carid": "X20S43",
      "grpid": "103"
    }
  },
  {
    "id": 8823,
    "type": "instant",
    "field": "latitude",
    "original_value": "22.551674",
    "new_value": "5.637624",
    "delta": "-16.914049801363483",
    "meta": {
      "carid": "X987G3",
      "grpid": "52"
    }
  },
  {
    "id": 8864,
    "type": "bias",
    "field": "direction",
    "original_value": "0.0",
    "new_value": "43.8",
    "delta": "43.80622552480177",
    "meta": {
      "carid": "XA5G44",
      "grpid": "57"
    }
  },
  {
    "id": 8872,
    "type": "bias",
    "field": "speed",
    "original_value": "0.0",
    "new_value": "108.1",
    "delta": "108.14751032560122",
    "meta": {
      "carid": "X65F70",
      "grpid": "57"
    }
  },
  {
    "id": 8905,
    "type": "bias",
    "field": "speed",
    "original_value": "0.0",
    "new_value": "206.7",
    "delta": "206.68637522739294",
    "meta": {
      "carid": "X364K5",
      "grpid": "52"
    }
  },
  {
    "id": 8934,
    "type": "bias",
    "field": "speed",
    "original_value": "12.0",
    "new_value": "244.5",
    "delta": "232.50555489859116",
    "meta": {
      "carid": "X57L82",
      "grpid": "84"
    }
  },
  {
    "id": 8957,
    "type": "instant",
    "field": "direction",
    "original_value": "270.0",
    "new_value": "18.0",
    "delta": "-252.0248164662206",
    "meta": {
      "carid": "X860U3",
      "grpid": "60"
    }
  },
  {
    "id": 8959,
    "type": "bias",
    "field": "direction",
    "original_value": "90.0",
    "new_value": "13.0",
    "delta": "-76.99525134915146",
    "meta": {
      "carid": "X333U5",
      "grpid": "59"
    }
  },
  {
    "id": 8971,
    "type": "bias",
    "field": "latitude",
    "original_value": "22.527193",
    "new_value": "47.322567",
    "delta": "24.795373715862905",
    "meta": {
      "carid": "XQR415",
      "grpid": "60"
    }
  },
  {
    "id": 9017,
    "type": "bias",
    "field": "direction",
    "original_value": "0.0",
    "new_value": "51.5",
    "delta": "51.52872633241274",
    "meta": {
      "carid": "XA5G44",
      "grpid": "58"
    }
  },
  {
    "id": 9028,
    "type": "bias",
    "field": "speed",
    "original_value": "0.0",
    "new_value": "180.3",
    "delta": "180.33354103795864",
    "meta": {
      "carid": "X65F70",
      "grpid": "58"
    }
  },
  {
    "id": 9037,
    "type": "instant",
    "field": "longitude",
    "original_value": "114.130490",
    "new_value": "-79.986841",
    "delta": "-194.11733080623156",
    "meta": {
      "carid": "X57L80",
      "grpid": "72"
    }
  },
  {
    "id": 9047,
    "type": "bias",
    "field": "direction",
    "original_value": "0.0",
    "new_value": "263.7",
    "delta": "263.6713247866848",
    "meta": {
      "carid": "X35G03",
      "grpid": "51"
    }
  },
  {
    "id": 9121,
    "type": "bias",
    "field": "direction",
    "original_value": "45.0",
    "new_value": "142.6",
    "delta": "97.56546073359632",
    "meta": {
      "carid": "X35G03",
      "grpid": "52"
    }
  },
  {
    "id": 9140,
    "type": "bias",
    "field": "latitude",
    "original_value": "22.526014",
    "new_value": "-47.149755",
    "delta": "-69.67576907127392",
    "meta": {
      "carid": "XQR415",
      "grpid": "61"
    }
  },
  {
    "id": 9156,
    "type": "bias",
    "field": "longitude",
    "original_value": "114.119020",
    "new_value": "36.007402",
    "delta": "-78.1116178207973",
    "meta": {
      "carid": "X369R0",
      "grpid": "21"
    }
  },
  {
    "id": 9162,
    "type": "drift",
    "field": "latitude",
    "original_value": "22.609482",
    "new_value": "-5.566906",
    "delta": "-28.176388179936982",
    "meta": {
      "carid": "X701U5",
      "grpid": "52"
    }
  },
  {
    "id": 9169,
    "type": "instant",
    "field": "longitude",
    "original_value": "113.991140",
    "new_value": "-51.432451",
    "delta": "-165.4235913597043",
    "meta": {
      "carid": "X403Z5",
      "grpid": "54"
    }
  },
  {
    "id": 9211,
    "type": "bias",
    "field": "speed",
    "original_value": "19.0",
    "new_value": "226.5",
    "delta": "207.47177101172124",
    "meta": {
      "carid": "X831U7",
      "grpid": "58"
    }
  },
  {
    "id": 9232,
    "type": "instant",
    "field": "direction",
    "original_value": "135.0",
    "new_value": "70.0",
    "delta": "-65.02181903741628",
    "meta": {
      "carid": "X20S52",
      "grpid": "70"
    }
  },
  {
    "id": 9282,
    "type": "instant",
    "field": "speed",
    "original_value": "1.0",
    "new_value": "189.0",
    "delta": "188.01517084043368",
    "meta": {
      "carid": "X357Z2",
      "grpid": "62"
    }
  },
  {
    "id": 9297,
    "type": "bias",
    "field": "latitude",
    "original_value": "22.537733",
    "new_value": "-20.382531",
    "delta": "-42.92026414845549",
    "meta": {
      "carid": "X57L82",
      "grpid": "90"
    }
  },
  {
    "id": 9304,
    "type": "instant",
    "field": "latitude",
    "original_value": "22.653078",
    "new_value": "69.650061",
    "delta": "46.99698292394054",
    "meta": {
      "carid": "X853U3",
      "grpid": "55"
    }
  },
  {
    "id": 9336,
    "type": "drift",
    "field": "latitude",
    "original_value": "22.607191",
    "new_value": "-87.191624",
    "delta": "-109.79881540172565",
    "meta": {
      "carid": "X701U5",
      "grpid": "53"
    }
  },
  {
    "id": 9384,
    "type": "bias",
    "field": "speed",
    "original_value": "54.0",
    "new_value": "210.7",
    "delta": "156.71448422018926",
    "meta": {
      "carid": "X831U7",
      "grpid": "59"
    }
  },
  {
    "id": 9385,
    "type": "instant",
    "field": "speed",
    "original_value": "68.0",
    "new_value": "225.4",
    "delta": "157.4110919123653",
    "meta": {
      "carid": "X964G7",
      "grpid": "58"
    }
  },
  {
    "id": 9398,
    "type": "bias",
    "field": "latitude",
    "original_value": "22.600183",
    "new_value": "-3.794372",
    "delta": "-26.394554635256064",
    "meta": {
      "carid": "X56L55",
      "grpid": "109"
    }
  },
  {
    "id": 9458,
    "type": "instant",
    "field": "latitude",
    "original_value": "22.599890",
    "new_value": "-60.607073",
    "delta": "-83.20696255331856",
    "meta": {
      "carid": "X51L21",
      "grpid": "111"
    }
  },
  {
    "id": 9459,
    "type": "bias",
    "field": "latitude",
    "original_value": "22.538382",
    "new_value": "45.142388",
    "delta": "22.604005797561832",
    "meta": {
      "carid": "X57L82",
      "grpid": "91"
    }
  },
  {
    "id": 9477,
    "type": "bias",
    "field": "direction",
    "original_value": "45.0",
    "new_value": "309.1",
    "delta": "264.0853018076972",
    "meta": {
      "carid": "X777D1",
      "grpid": "62"
    }
  },
  {
    "id": 9509,
    "type": "drift",
    "field": "latitude",
    "original_value": "22.552912",
    "new_value": "1.919147",
    "delta": "-20.633764628574596",
    "meta": {
      "carid": "X166F7",
      "grpid": "55"
    }
  },
  {
    "id": 9514,
    "type": "bias",
    "field": "longitude",
    "original_value": "113.918870",
    "new_value": "165.699647",
    "delta": "51.78077698006169",
    "meta": {
      "carid": "X766D3",
      "grpid": "62"
    }
  },
  {
    "id": 9519,
    "type": "instant",
    "field": "direction",
    "original_value": "45.0",
    "new_value": "108.6",
    "delta": "63.5591823293953",
    "meta": {
      "carid": "X266U7",
      "grpid": "63"
    }
  },
  {
    "id": 9540,
    "type": "bias",
    "field": "latitude",
    "original_value": "22.602365",
    "new_value": "83.299332",
    "delta": "60.69696655529726",
    "meta": {
      "carid": "X56L55",
      "grpid": "110"
    }
  },
  {
    "id": 9542,
    "type": "instant",
    "field": "latitude",
    "original_value": "22.540182",
    "new_value": "60.158875",
    "delta": "37.618692910764715",
    "meta": {
      "carid": "X95P51",
      "grpid": "62"
    }
  },
  {
    "id": 9559,
    "type": "bias",
    "field": "speed",
    "original_value": "24.0",
    "new_value": "170.5",
    "delta": "146.46305380771952",
    "meta": {
      "carid": "X20S52",
      "grpid": "73"
    }
  },
  {
    "id": 9574,
    "type": "bias",
    "field": "speed",
    "original_value": "37.0",
    "new_value": "222.4",
    "delta": "185.39883009968156",
    "meta": {
      "carid": "X20S52",
      "grpid": "74"
    }
  },
  {
    "id": 9624,
    "type": "bias",
    "field": "direction",
    "original_value": "45.0",
    "new_value": "337.1",
    "delta": "292.13664044935575",
    "meta": {
      "carid": "X777D1",
      "grpid": "63"
    }
  },
  {
    "id": 9654,
    "type": "instant",
    "field": "speed",
    "original_value": "87.0",
    "new_value": "124.5",
    "delta": "37.49807070489017",
    "meta": {
      "carid": "X35G10",
      "grpid": "95"
    }
  },
  {
    "id": 9656,
    "type": "bias",
    "field": "longitude",
    "original_value": "114.119020",
    "new_value": "-162.708948",
    "delta": "-276.82796789378915",
    "meta": {
      "carid": "X369R0",
      "grpid": "22"
    }
  },
  {
    "id": 9663,
    "type": "bias",
    "field": "longitude",
    "original_value": "113.918870",
    "new_value": "-172.915090",
    "delta": "-286.83395984113895",
    "meta": {
      "carid": "X766D3",
      "grpid": "63"
    }
  },
  {
    "id": 9675,
    "type": "drift",
    "field": "speed",
    "original_value": "0.0",
    "new_value": "58.6",
    "delta": "58.58992874388871",
    "meta": {
      "carid": "X980G1",
      "grpid": "57"
    }
  },
  {
    "id": 9676,
    "type": "drift",
    "field": "latitude",
    "original_value": "22.551662",
    "new_value": "-28.573034",
    "delta": "-51.1246958806216",
    "meta": {
      "carid": "X166F7",
      "grpid": "56"
    }
  },
  {
    "id": 9703,
    "type": "instant",
    "field": "direction",
    "original_value": "45.0",
    "new_value": "167.0",
    "delta": "121.9728002228724",
    "meta": {
      "carid": "X28X43",
      "grpid": "63"
    }
  },
  {
    "id": 9712,
    "type": "drift",
    "field": "speed",
    "original_value": "53.0",
    "new_value": "154.5",
    "delta": "101.4994957260555",
    "meta": {
      "carid": "X964G7",
      "grpid": "60"
    }
  },
  {
    "id": 9753,
    "type": "bias",
    "field": "direction",
    "original_value": "180.0",
    "new_value": "137.7",
    "delta": "-42.32596201429945",
    "meta": {
      "carid": "X50F20",
      "grpid": "63"
    }
  },
  {
    "id": 9762,
    "type": "instant",
    "field": "longitude",
    "original_value": "114.130745",
    "new_value": "146.837120",
    "delta": "32.70637455877777",
    "meta": {
      "carid": "XQR425",
      "grpid": "62"
    }
  },
  {
    "id": 9774,
    "type": "bias",
    "field": "direction",
    "original_value": "45.0",
    "new_value": "196.6",
    "delta": "151.6402244676961",
    "meta": {
      "carid": "X777D1",
      "grpid": "64"
    }
  },
  {
    "id": 9779,
    "type": "instant",
    "field": "longitude",
    "original_value": "114.022030",
    "new_value": "-43.899575",
    "delta": "-157.92160531317708",
    "meta": {
      "carid": "X620D1",
      "grpid": "62"
    }
  },
  {
    "id": 9816,
    "type": "bias",
    "field": "longitude",
    "original_value": "113.918870",
    "new_value": "-29.007609",
    "delta": "-142.92647907250083",
    "meta": {
      "carid": "X766D3",
      "grpid": "64"
    }
  },
  {
    "id": 9821,
    "type": "instant",
    "field": "direction",
    "original_value": "270.0",
    "new_value": "126.6",
    "delta": "-143.39529911506241",
    "meta": {
      "carid": "X31W87",
      "grpid": "64"
    }
  },
  {
    "id": 9843,
    "type": "drift",
    "field": "latitude",
    "original_value": "22.547758",
    "new_value": "-44.933243",
    "delta": "-67.48100131218185",
    "meta": {
      "carid": "X166F7",
      "grpid": "57"
    }
  },
  {
    "id": 9845,
    "type": "drift",
    "field": "speed",
    "original_value": "43.0",
    "new_value": "163.5",
    "delta": "120.47716945383218",
    "meta": {
      "carid": "X980G1",
      "grpid": "58"
    }
  },
  {
    "id": 9882,
    "type": "drift",
    "field": "speed",
    "original_value": "55.0",
    "new_value": "200.9",
    "delta": "145.91808880284233",
    "meta": {
      "carid": "X964G7",
      "grpid": "61"
    }
  },
  {
    "id": 9902,
    "type": "bias",
    "field": "direction",
    "original_value": "180.0",
    "new_value": "220.9",
    "delta": "40.922576054881944",
    "meta": {
      "carid": "X50F20",
      "grpid": "64"
    }
  },
  {
    "id": 9910,
    "type": "instant",
    "field": "longitude",
    "original_value": "113.879920",
    "new_value": "4.661700",
    "delta": "-109.21822028783863",
    "meta": {
      "carid": "X253U7",
      "grpid": "63"
    }
  },
  {
    "id": 9913,
    "type": "drift",
    "field": "longitude",
    "original_value": "114.068985",
    "new_value": "-24.785507",
    "delta": "-138.85449225758603",
    "meta": {
      "carid": "X364K5",
      "grpid": "58"
    }
  },
  {
    "id": 9926,
    "type": "instant",
    "field": "latitude",
    "original_value": "22.558365",
    "new_value": "-61.053573",
    "delta": "-83.61193761118638",
    "meta": {
      "carid": "X10S45",
      "grpid": "100"
    }
  },
  {
    "id": 9968,
    "type": "instant",
    "field": "direction",
    "original_value": "90.0",
    "new_value": "181.7",
    "delta": "91.72713146392826",
    "meta": {
      "carid": "X332D7",
      "grpid": "65"
    }
  },
  {
    "id": 9973,
    "type": "instant",
    "field": "latitude",
    "original_value": "22.541218",
    "new_value": "-73.677007",
    "delta": "-96.21822500820244",
    "meta": {
      "carid": "X31W87",
      "grpid": "65"
    }
  },
  {
    "id": 10009,
    "type": "drift",
    "field": "speed",
    "original_value": "43.0",
    "new_value": "183.7",
    "delta": "140.6977262265212",
    "meta": {
      "carid": "X980G1",
      "grpid": "59"
    }
  },
  {
    "id": 10035,
    "type": "bias",
    "field": "speed",
    "original_value": "0.0",
    "new_value": "30.8",
    "delta": "30.826369419887783",
    "meta": {
      "carid": "X20S21",
      "grpid": "105"
    }
  },
  {
    "id": 10045,
    "type": "drift",
    "field": "speed",
    "original_value": "14.0",
    "new_value": "171.1",
    "delta": "157.06744943746133",
    "meta": {
      "carid": "X964G7",
      "grpid": "62"
    }
  },
  {
    "id": 10077,
    "type": "drift",
    "field": "longitude",
    "original_value": "114.068985",
    "new_value": "-52.252987",
    "delta": "-166.32197219903838",
    "meta": {
      "carid": "X364K5",
      "grpid": "59"
    }
  },
  {
    "id": 10130,
    "type": "bias",
    "field": "speed",
    "original_value": "0.0",
    "new_value": "158.0",
    "delta": "157.99887542952422",
    "meta": {
      "carid": "X20S21",
      "grpid": "106"
    }
  },
  {
    "id": 10159,
    "type": "instant",
    "field": "latitude",
    "original_value": "22.607649",
    "new_value": "-68.737355",
    "delta": "-91.34500441202523",
    "meta": {
      "carid": "X56L62",
      "grpid": "93"
    }
  }
]